MANIFEST.in
README.rst
setup.py
XStatic_React.egg-info/PKG-INFO
XStatic_React.egg-info/SOURCES.txt
XStatic_React.egg-info/dependency_links.txt
XStatic_React.egg-info/namespace_packages.txt
XStatic_React.egg-info/not-zip-safe
XStatic_React.egg-info/top_level.txt
xstatic/__init__.py
xstatic/pkg/__init__.py
xstatic/pkg/react/__init__.py
xstatic/pkg/react/data/JSXtransformer.js
xstatic/pkg/react/data/react.min.js
xstatic/pkg/react/data/reactable.js