Metadata-Version: 1.0
Name: XStatic-React
Version: 0.12.2.1
Summary: React 0.12.2 (XStatic packaging standard)
Home-page: https://facebook.github.io/react/
Author: Michael Kuty
Author-email: mail@majklk.cz
License: (same as React)
Keywords: react xstatic
Platform: any
